adspower/__init__.py
adspower/adspower.py
adspower/consts.py
adspower/errors.py
adspower/models.py
py_adspower-1.1.dist-info/METADATA
py_adspower-1.1.dist-info/WHEEL
py_adspower-1.1.dist-info/top_level.txt
py_adspower-1.1.dist-info/RECORD
